{"title":"Divinations","url":"https://every.to/divinations?sort=newest","favicon":"https://every.to/favicon.ico","elements":[{"title":"The Infinite Article","contents":"How close are we to having a personal AI<br data-owner=\"balance-text\">that can write the perfect thing just for us?","link":"https://every.to/divinations/the-infinite-article","retrieved":1664433698107},{"title":"Figma’s Layered Lessons","contents":"Or, how to learn something useful from big events","link":"https://every.to/divinations/figma-s-layered-lessons","retrieved":1663829225387},{"title":"What is a Business?","contents":"An expansive question that has surprisingly practical value","link":"https://every.to/divinations/what-is-a-business","retrieved":1663223248866},{"title":"Book Review: Slouching Towards Utopia","contents":"The origins of economic progress, and what comes next","link":"https://every.to/divinations/book-review-slouching-towards-utopia","retrieved":1662618424634},{"title":"Intelligent Tools","contents":"A third revolution in software is happening,<br data-owner=\"balance-text\">and we’re just beginning to understand it.","link":"https://every.to/divinations/intelligent-tools","retrieved":1662054274083},{"title":"⚠️ Time to BeWorried ⚠️","contents":"Viral photo app BeReal has a unique<br data-owner=\"balance-text\">feature, but not a unique network.","link":"https://every.to/divinations/bereal-should-beworried","retrieved":1661449263331},{"title":"How Every Executes: two tweaks thatgenerated ~54% more paid subscribers","contents":"Real data from our business showing<br data-owner=\"balance-text\">how execution is exponential","link":"https://every.to/divinations/how-every-executes-two-tweaks-that-generated-54-more-paid-subscribers","retrieved":1660801911677},{"title":"Execution is Exponential","contents":"The math that quantifies how much execution matters","link":"https://every.to/divinations/execution-is-exponential","retrieved":1660196399300},{"title":"How Power Works in the Writing Industry","contents":"A market analysis, Divinations-style","link":"https://every.to/divinations/how-power-works-in-the-writing-industry","retrieved":1659635145904},{"title":"Instagram’s Existential Bet","contents":"They’re betting the farm on Reels.<br data-owner=\"balance-text\">Will it blow up in their face?","link":"https://every.to/divinations/instagram-s-existential-bet","retrieved":1658987042518},{"title":"Finding Power: How To Do Market Analysis","contents":"A step-by-step process for uncovering the<br data-owner=\"balance-text\">power dynamics that govern any industry","link":"https://every.to/divinations/finding-power-how-to-do-market-analysis","retrieved":1658382414592},{"title":"Did Medium Succeed?","contents":"The past, present, and future of writing on the internet","link":"https://every.to/divinations/did-medium-succeed","retrieved":1657777782417},{"title":"What kind of company do you want to build?","contents":"Scale, speed, or freedom: choose two","link":"https://every.to/divinations/what-kind-of-company-do-you-want-to-build","retrieved":1656611376062},{"title":"How To Time The Market (Or Not)","contents":"A Book Review of “Mastering the Market Cycle”","link":"https://every.to/divinations/how-to-time-the-market-or-not","retrieved":1653068889428},{"title":"Mastering the MarketCycle, by Howard Marks","contents":"My chapter-by-chapter summary, with notes and reactions","link":"https://every.to/divinations/mastering-the-market-cycle-by-howard-marks","retrieved":1653068889429},{"title":"Why Sh*t is Hitting the Fan","contents":"How the Fed accidentally scuttled<br data-owner=\"balance-text\">your Series B, simply explained","link":"https://every.to/divinations/why-sh-t-is-hitting-the-fan","retrieved":1652637475777},{"title":"Map of a Downturn","contents":"Untangling the complex causal<br data-owner=\"balance-text\">chain that makes good times go bad","link":"https://every.to/divinations/map-of-a-downturn","retrieved":1651945188873},{"title":"Twitter as a City-State","contents":"The Argument for Democracy in Cyberspace","link":"https://every.to/divinations/twitter-as-a-city-state","retrieved":1651383671187},{"title":"DALL·E 2 and The Origin of Vibe Shifts","contents":"By Means of Natural Selection","link":"https://every.to/divinations/dall-e-2-and-the-origin-of-vibe-shifts","retrieved":1650649679168},{"title":"Elon is Right: Twitter ShouldOpen Up the Algorithm","contents":"Commoditizing tweets’ complement (the<br data-owner=\"balance-text\">algorithm) will increase usage and rebuild trust","link":"https://every.to/divinations/elon-is-right-twitter-should-open-up-the-algorithm","retrieved":1650130710258},{"title":"Friendly Competition and Subtle Defection","contents":"My wife and I recently bought our first home<br data-owner=\"balance-text\">and we’re expecting our first child soon, so, as<br data-owner=\"balance-text\">you can imagine, we’ve been doing a lot of wor","link":"https://every.to/divinations/friendly-competition-and-subtle-defection","retrieved":1649396192381},{"title":"Recursive Publishing","contents":"A force to be reckoned with","link":"https://every.to/divinations/recursive-publishing","retrieved":1648791358120},{"title":"Screw it, I’m investing in Peloton","contents":"I’m in at $22.51—we’ll see what happens next.","link":"https://every.to/divinations/screw-it-i-m-investing-in-peloton","retrieved":1648013733330},{"title":"Substack’s Ideology","contents":"The point isn’t just to make money—it’s to change the<br data-owner=\"balance-text\">systems that human attention flows through. You can’t<br data-owner=\"balance-text\">understand Substack without understanding this.","link":"https://every.to/divinations/substack-s-ideology","retrieved":1647452290470},{"title":"How To Buy The Dip","contents":"Is now a great time to buy? Or a terrible one?","link":"https://every.to/divinations/how-to-buy-the-dip","retrieved":1647063330765}]}